Metadata-Version: 1.1
Name: great-sitemap-search
Version: 0.2
Summary: A really simple search backend for your site based on a crawler that scanns all pages in sitemap.xml
Home-page: http://www.webkrafts.net/
Author: Michael Schmidt
Author-email: ms@webkrafts.net
License: BSD License
Platform: UNKNOWN
Classifier: Environment :: Web Environment
Classifier: Framework :: Django
Classifier: Intended Audience :: Developers
Classifier: License :: OSI Approved :: BSD License
Classifier: Operating System :: OS Independent
Classifier: Programming Language :: Python
